Metadata-Version: 2.1
Name: telnetlib2
Version: 1.0.0
Summary: simple telnet module
Home-page: https://github.com/AlaBouali/telnetlib2
Author: AlaBouali
Author-email: trap.leader.123@gmail.com
License: MIT License
Platform: UNKNOWN
Classifier: Programming Language :: Python
Classifier: License :: OSI Approved :: MIT License 
Requires-Python: >=2.7
